<annotation>
  <folder/>
  <filename>sunny2-060.jpg</filename>
  <database>The VOC2007 Database</database>
  <annotation>Pascal VOC2007</annotation>
  <image/>
  <size>
    <height>720</height>
    <width>1280</width>
    <depth>3</depth>
  </size>
  <segmented/>
  <object>
    <name>car</name>
    <pose/>
    <truncated/>
    <difficult/>
    <bndbox>
      <xmin>51.78151260504202</xmin>
      <ymin>384.1932773109244</ymin>
      <xmax>130.7731092436975</xmax>
      <ymax>442.17647058823536</ymax>
    </bndbox>
  </object>
  <object>
    <name>car</name>
    <pose/>
    <truncated/>
    <difficult/>
    <bndbox>
      <xmin>107.2436974789916</xmin>
      <ymin>382.51260504201684</ymin>
      <xmax>236.65546218487395</xmax>
      <ymax>454.78151260504205</ymax>
    </bndbox>
  </object>
  <object>
    <name>car</name>
    <pose/>
    <truncated/>
    <difficult/>
    <bndbox>
      <xmin>288.7563025210084</xmin>
      <ymin>386.7142857142857</ymin>
      <xmax>402.20168067226894</xmax>
      <ymax>453.1008403361345</ymax>
    </bndbox>
  </object>
  <object>
    <name>bus</name>
    <pose/>
    <truncated/>
    <difficult/>
    <bndbox>
      <xmin>181.19327731092437</xmin>
      <ymin>373.2689075630252</ymin>
      <xmax>281.1932773109244</xmax>
      <ymax>422.8487394957983</ymax>
    </bndbox>
  </object>
  <object>
    <name>car</name>
    <pose/>
    <truncated/>
    <difficult/>
    <bndbox>
      <xmin>430.7731092436975</xmin>
      <ymin>401.0</ymin>
      <xmax>464.38655462184875</xmax>
      <ymax>426.2100840336135</ymax>
    </bndbox>
  </object>
  <object>
    <name>car</name>
    <pose/>
    <truncated/>
    <difficult/>
    <bndbox>
      <xmin>465.22689075630257</xmin>
      <ymin>404.36134453781517</ymin>
      <xmax>523.2100840336135</xmax>
      <ymax>433.7731092436975</ymax>
    </bndbox>
  </object>
  <object>
    <name>car</name>
    <pose/>
    <truncated/>
    <difficult/>
    <bndbox>
      <xmin>550.1008403361345</xmin>
      <ymin>401.0</ymin>
      <xmax>577.8319327731093</xmax>
      <ymax>423.6890756302521</ymax>
    </bndbox>
  </object>
</annotation>
