<annotation>
  <folder/>
  <filename>sunny3-148.jpg</filename>
  <database>YoloV3</database>
  <annotation>YoloV3_car_bus_sunny3</annotation>
  <image/>
  <size>
    <height>720</height>
    <width>1280</width>
    <depth>3</depth>
  </size>
  <segmented/>
  <object>
    <name>car</name>
    <pose/>
    <truncated/>
    <difficult/>
    <bndbox>
      <xmin>575.3109243697479</xmin>
      <ymin>405.20168067226894</ymin>
      <xmax>618.1680672268908</xmax>
      <ymax>443.8571428571429</ymax>
    </bndbox>
  </object>
  <object>
    <name>car</name>
    <pose/>
    <truncated/>
    <difficult/>
    <bndbox>
      <xmin>447.5798319327731</xmin>
      <ymin>401.0</ymin>
      <xmax>519.8487394957983</xmax>
      <ymax>448.0588235294118</ymax>
    </bndbox>
  </object>
  <object>
    <name>car</name>
    <pose/>
    <truncated/>
    <difficult/>
    <bndbox>
      <xmin>17.327731092436977</xmin>
      <ymin>383.3529411764706</ymin>
      <xmax>178.67226890756302</xmax>
      <ymax>472.42857142857144</ymax>
    </bndbox>
  </object>
</annotation>
